config_spec/__init__.py
config_spec/config_spec.py
config_spec-0.0.5.dist-info/LICENSE
config_spec-0.0.5.dist-info/METADATA
config_spec-0.0.5.dist-info/WHEEL
config_spec-0.0.5.dist-info/top_level.txt
config_spec-0.0.5.dist-info/RECORD
