Metadata-Version: 2.1
Name: config-spec
Version: 0.0.5
Summary: JSON-parseable configuration of classes and functions
Author-email: Dibya Ghosh <dibya.ghosh@berkeley.edu>
Project-URL: Homepage, https://github.com/dibyaghosh/config_spec
Classifier: Programming Language :: Python :: 3
Classifier: License :: OSI Approved :: MIT License
Classifier: Operating System :: OS Independent
Requires-Python: >=3.8
License-File: LICENSE
